spinenet/__init__.py
spinenet/main.py
spinenet/io/__init__.py
spinenet/io/dicom_io.py
spinenet/io/download.py
spinenet/io/save_results.py
spinenet/models/__init__.py
spinenet/models/appearance.py
spinenet/models/context.py
spinenet/models/grading.py
spinenet/models/vfr.py
spinenet/utils/__init__.py
spinenet/utils/accuracy_scores.py
spinenet/utils/classification.py
spinenet/utils/detect_and_group.py
spinenet/utils/detection_post_processing.py
spinenet/utils/discard_outliers.py
spinenet/utils/extract_volumes.py
spinenet/utils/gen_utils.py
spinenet/utils/gt_formatting.py
spinenet/utils/label_verts.py
spinenet/utils/scan_preprocessing.py
spinenet-2.0.4.dist-info/METADATA
spinenet-2.0.4.dist-info/WHEEL
spinenet-2.0.4.dist-info/entry_points.txt
spinenet-2.0.4.dist-info/licenses/LICENCE.md
spinenet-2.0.4.dist-info/RECORD
