Metadata-Version: 2.4
Name: spinenet
Version: 2.0.4
Summary: Automated software for analysing clinical spinal MRI scans.
Author: Rhydian Windsor
Author-email: Maria Monzon <mmonzon@ethz.ch>
License-File: LICENCE.md
Keywords: MRI,deep-learning,medical-imaging,segmentation,spine
Classifier: Development Status :: 3 - Alpha
Classifier: Intended Audience :: Science/Research
Classifier: License :: OSI Approved :: MIT License
Classifier: Programming Language :: Python :: 3.9
Classifier: Programming Language :: Python :: 3.10
Classifier: Programming Language :: Python :: 3.11
Classifier: Programming Language :: Python :: 3.12
Classifier: Topic :: Scientific/Engineering :: Medical Science Apps.
Requires-Python: <3.12,>=3.9
Requires-Dist: matplotlib>=3.5.0
Requires-Dist: nibabel>=3.2.0
Requires-Dist: numpy<2
Requires-Dist: numpy>=1.20.0
Requires-Dist: opencv-python<4.8.0.76,>=4.5.0
Requires-Dist: pandas>=1.3.0
Requires-Dist: pydicom
Requires-Dist: requests
Requires-Dist: scikit-image>=0.19.0
Requires-Dist: scipy>=1.7.0
Requires-Dist: shapely
Requires-Dist: torch<=2.5.0,>=2.0.0
Requires-Dist: torchvision>=0.15.0
Requires-Dist: tqdm
Provides-Extra: dev
Requires-Dist: black>=22.0.0; extra == 'dev'
Requires-Dist: mypy>=1.0.0; extra == 'dev'
Requires-Dist: pytest-cov>=4.0.0; extra == 'dev'
Requires-Dist: pytest>=7.0.0; extra == 'dev'
Requires-Dist: ruff>=0.1.0; extra == 'dev'
Provides-Extra: vis
Requires-Dist: matplotlib>=3.5.0; extra == 'vis'
Requires-Dist: plotly>=5.0.0; extra == 'vis'
Requires-Dist: seaborn>=0.11.0; extra == 'vis'
